{
  "coverage": "63.34%",
  "expectCount": 532,
  "actualCount": 337,
  "files": {
    "src/js/algorithm/abstract-algorithm.js": {
      "expectCount": 4,
      "actualCount": 3,
      "undocumentLines": [
        89
      ]
    },
    "src/js/algorithm/algorithm-result.js": {
      "expectCount": 7,
      "actualCount": 5,
      "undocumentLines": [
        27,
        26
      ]
    },
    "src/js/tool/algorithm-tool.js": {
      "expectCount": 11,
      "actualCount": 9,
      "undocumentLines": [
        80,
        89
      ]
    },
    "src/js/ui/canvas.js": {
      "expectCount": 21,
      "actualCount": 0,
      "undocumentLines": [
        6,
        23,
        60,
        21,
        24,
        29,
        53,
        54,
        64,
        76,
        27,
        107,
        28,
        52,
        33,
        37,
        47,
        43,
        48,
        22,
        88
      ]
    },
    "src/js/algorithm/change.js": {
      "expectCount": 9,
      "actualCount": 5,
      "undocumentLines": [
        43,
        41,
        44,
        42
      ]
    },
    "src/js/data/node/circle-node.js": {
      "expectCount": 10,
      "actualCount": 9,
      "undocumentLines": [
        20
      ]
    },
    "src/js/ui/context-menu.js": {
      "expectCount": 13,
      "actualCount": 0,
      "undocumentLines": [
        13,
        108,
        28,
        31,
        104,
        35,
        83,
        105,
        106,
        30,
        86,
        77,
        29
      ]
    },
    "src/js/data/edge/dashed-edge.js": {
      "expectCount": 2,
      "actualCount": 2,
      "undocumentLines": []
    },
    "src/js/data/node/diamond-node.js": {
      "expectCount": 4,
      "actualCount": 2,
      "undocumentLines": [
        17,
        18
      ]
    },
    "src/js/ui/dropdown.js": {
      "expectCount": 20,
      "actualCount": 13,
      "undocumentLines": [
        120,
        121,
        219,
        122,
        123,
        58,
        194
      ]
    },
    "src/js/data/edge/edge.js": {
      "expectCount": 21,
      "actualCount": 13,
      "undocumentLines": [
        122,
        52,
        121,
        76,
        87,
        61,
        51,
        120
      ]
    },
    "src/js/tool/edge-tool.js": {
      "expectCount": 8,
      "actualCount": 6,
      "undocumentLines": [
        87,
        86
      ]
    },
    "src/js/tool/erase-tool.js": {
      "expectCount": 5,
      "actualCount": 5,
      "undocumentLines": []
    },
    "src/js/data/graph.js": {
      "expectCount": 16,
      "actualCount": 14,
      "undocumentLines": [
        19,
        18
      ]
    },
    "src/js/data/node/hexagon-node.js": {
      "expectCount": 4,
      "actualCount": 2,
      "undocumentLines": [
        17,
        18
      ]
    },
    "src/js/data/label.js": {
      "expectCount": 11,
      "actualCount": 7,
      "undocumentLines": [
        48,
        100,
        46,
        47
      ]
    },
    "src/js/util/line-2d.js": {
      "expectCount": 5,
      "actualCount": 3,
      "undocumentLines": [
        26,
        27
      ]
    },
    "src/js/util/mouse-handler.js": {
      "expectCount": 27,
      "actualCount": 0,
      "undocumentLines": [
        8,
        39,
        40,
        30,
        202,
        195,
        216,
        226,
        212,
        184,
        45,
        37,
        31,
        42,
        154,
        41,
        100,
        34,
        145,
        146,
        143,
        144,
        163,
        151,
        36,
        66,
        174
      ]
    },
    "src/js/tool/move-tool.js": {
      "expectCount": 10,
      "actualCount": 6,
      "undocumentLines": [
        29,
        30,
        27,
        28
      ]
    },
    "src/js/data/node/node.js": {
      "expectCount": 11,
      "actualCount": 9,
      "undocumentLines": [
        39,
        40
      ]
    },
    "src/js/tool/node-tool.js": {
      "expectCount": 5,
      "actualCount": 5,
      "undocumentLines": []
    },
    "src/js/data/node/octagon-node.js": {
      "expectCount": 4,
      "actualCount": 2,
      "undocumentLines": [
        17,
        18
      ]
    },
    "src/js/tool/pan-tool.js": {
      "expectCount": 7,
      "actualCount": 6,
      "undocumentLines": [
        79
      ]
    },
    "src/js/data/node/pentagon-node.js": {
      "expectCount": 4,
      "actualCount": 2,
      "undocumentLines": [
        17,
        18
      ]
    },
    "src/js/util/point-2d.js": {
      "expectCount": 10,
      "actualCount": 8,
      "undocumentLines": [
        31,
        32
      ]
    },
    "src/js/data/node/polygon-node.js": {
      "expectCount": 10,
      "actualCount": 9,
      "undocumentLines": [
        23
      ]
    },
    "src/js/util/queue.js": {
      "expectCount": 11,
      "actualCount": 9,
      "undocumentLines": [
        19,
        18
      ]
    },
    "src/js/tool/select-move-tool.js": {
      "expectCount": 8,
      "actualCount": 8,
      "undocumentLines": []
    },
    "src/js/tool/select-tool.js": {
      "expectCount": 5,
      "actualCount": 4,
      "undocumentLines": [
        46
      ]
    },
    "src/js/util/graph-serialize.js": {
      "expectCount": 20,
      "actualCount": 12,
      "undocumentLines": [
        52,
        70,
        82,
        78,
        54,
        57,
        53,
        62
      ]
    },
    "src/js/ui/sidebar.js": {
      "expectCount": 11,
      "actualCount": 6,
      "undocumentLines": [
        87,
        89,
        49,
        57,
        48
      ]
    },
    "src/js/ui/sidebar-algorithm.js": {
      "expectCount": 14,
      "actualCount": 11,
      "undocumentLines": [
        266,
        32,
        33
      ]
    },
    "src/js/ui/sidebar-content.js": {
      "expectCount": 7,
      "actualCount": 5,
      "undocumentLines": [
        32,
        35
      ]
    },
    "src/js/ui/sidebar-display.js": {
      "expectCount": 4,
      "actualCount": 4,
      "undocumentLines": []
    },
    "src/js/ui/sidebar-select.js": {
      "expectCount": 10,
      "actualCount": 9,
      "undocumentLines": [
        67
      ]
    },
    "src/js/data/edge/solid-edge.js": {
      "expectCount": 2,
      "actualCount": 2,
      "undocumentLines": []
    },
    "src/js/data/node/square-node.js": {
      "expectCount": 4,
      "actualCount": 2,
      "undocumentLines": [
        17,
        18
      ]
    },
    "src/js/util/stack.js": {
      "expectCount": 10,
      "actualCount": 9,
      "undocumentLines": [
        12
      ]
    },
    "src/js/ui/status-bar.js": {
      "expectCount": 7,
      "actualCount": 5,
      "undocumentLines": [
        26,
        25
      ]
    },
    "src/js/algorithm/step.js": {
      "expectCount": 7,
      "actualCount": 6,
      "undocumentLines": [
        24
      ]
    },
    "src/js/algorithm/step-builder.js": {
      "expectCount": 9,
      "actualCount": 5,
      "undocumentLines": [
        40,
        39,
        38,
        48
      ]
    },
    "src/js/algorithm/stepper.js": {
      "expectCount": 13,
      "actualCount": 8,
      "undocumentLines": [
        77,
        34,
        21,
        15,
        13
      ]
    },
    "src/js/ui/tabs.js": {
      "expectCount": 22,
      "actualCount": 20,
      "undocumentLines": [
        22,
        23
      ]
    },
    "src/js/tool/tool.js": {
      "expectCount": 21,
      "actualCount": 20,
      "undocumentLines": [
        61
      ]
    },
    "src/js/ui/toolbar.js": {
      "expectCount": 10,
      "actualCount": 6,
      "undocumentLines": [
        95,
        101,
        62,
        61
      ]
    },
    "src/js/ui/top-bar.js": {
      "expectCount": 18,
      "actualCount": 0,
      "undocumentLines": [
        4,
        20,
        26,
        30,
        24,
        25,
        23,
        61,
        173,
        189,
        154,
        117,
        22,
        21,
        144,
        79,
        99,
        107
      ]
    },
    "src/js/algorithm/traversal-algorithm.js": {
      "expectCount": 12,
      "actualCount": 7,
      "undocumentLines": [
        188,
        148,
        139,
        83,
        84
      ]
    },
    "src/js/util/triangle-2d.js": {
      "expectCount": 8,
      "actualCount": 5,
      "undocumentLines": [
        35,
        36,
        37
      ]
    },
    "src/js/data/node/triangle-node.js": {
      "expectCount": 4,
      "actualCount": 2,
      "undocumentLines": [
        17,
        18
      ]
    },
    "src/js/ui/ui.js": {
      "expectCount": 11,
      "actualCount": 4,
      "undocumentLines": [
        59,
        67,
        57,
        58,
        56,
        55,
        88
      ]
    },
    "src/js/util/vector-2d.js": {
      "expectCount": 15,
      "actualCount": 13,
      "undocumentLines": [
        28,
        29
      ]
    },
    "src/js/util/bezier.js": {
      "expectCount": 2,
      "actualCount": 2,
      "undocumentLines": []
    },
    "src/js/ui/form.js": {
      "expectCount": 7,
      "actualCount": 7,
      "undocumentLines": []
    },
    "src/js/util/scroll-to-element.js": {
      "expectCount": 1,
      "actualCount": 1,
      "undocumentLines": []
    }
  }
}